<NotepadPlus>
    <UserLang name="Waxx" ext="" udlVersion="2.1">
        <Settings>
            <Global caseIgnored="no" allowFoldOfComments="yes" foldCompact="no" forcePureLC="0" decimalSeparator="0" />
            <Prefix Keywords1="no" Keywords2="no" Keywords3="no" Keywords4="no" Keywords5="no" Keywords6="no" Keywords7="yes" Keywords8="no" />
        </Settings>
        <KeywordLists>
            <Keywords name="Comments">00# 01 02 03; 03/* 04; 04*/</Keywords>
            <Keywords name="Numbers, prefix1"></Keywords>
            <Keywords name="Numbers, prefix2"></Keywords>
            <Keywords name="Numbers, extras1"></Keywords>
            <Keywords name="Numbers, extras2"></Keywords>
            <Keywords name="Numbers, suffix1"></Keywords>
            <Keywords name="Numbers, suffix2"></Keywords>
            <Keywords name="Numbers, range"></Keywords>
            <Keywords name="Operators1">= &gt; + , . - * % / \ : &lt; [ ] ( ) &amp;</Keywords>
            <Keywords name="Operators2"></Keywords>
            <Keywords name="Folders in code1, open">{</Keywords>
            <Keywords name="Folders in code1, middle"></Keywords>
            <Keywords name="Folders in code1, close">}</Keywords>
            <Keywords name="Folders in code2, open"></Keywords>
            <Keywords name="Folders in code2, middle"></Keywords>
            <Keywords name="Folders in code2, close"></Keywords>
            <Keywords name="Folders in comment, open"></Keywords>
            <Keywords name="Folders in comment, middle"></Keywords>
            <Keywords name="Folders in comment, close"></Keywords>
            <Keywords name="Keywords1"></Keywords>
            <Keywords name="Keywords2"></Keywords>
            <Keywords name="Keywords3">overhead&#x000D;&#x000A;null&#x000D;&#x000A;true&#x000D;&#x000A;false&#x000D;&#x000A;new&#x000D;&#x000A;import from&#x000D;&#x000A;of&#x000D;&#x000A;in&#x000D;&#x000A;|</Keywords>
            <Keywords name="Keywords4">class&#x000D;&#x000A;o&#x000D;&#x000A;func&#x000D;&#x000A;if&#x000D;&#x000A;else&#x000D;&#x000A;elif&#x000D;&#x000A;switch&#x000D;&#x000A;while&#x000D;&#x000A;for&#x000D;&#x000A;case&#x000D;&#x000A;my&#x000D;&#x000A;return&#x000D;&#x000A;break&#x000D;&#x000A;public&#x000D;&#x000A;static&#x000D;&#x000A;private&#x000D;&#x000A;protected&#x000D;&#x000A;default&#x000D;&#x000A;inline&#x000D;&#x000A;const&#x000D;&#x000A;override&#x000D;&#x000A;and&#x000D;&#x000A;or&#x000D;&#x000A;xor&#x000D;&#x000A;is&#x000D;&#x000A;not&#x000D;&#x000A;isnt&#x000D;&#x000A;throw&#x000D;&#x000A;try&#x000D;&#x000A;catch&#x000D;&#x000A;</Keywords>
            <Keywords name="Keywords5">this&#x000D;&#x000A;function</Keywords>
            <Keywords name="Keywords6"></Keywords>
            <Keywords name="Keywords7">#&#x000D;&#x000A;//</Keywords>
            <Keywords name="Keywords8"></Keywords>
            <Keywords name="Delimiters">00&quot; 01\ 02&quot; 03&apos; 04 05&apos; 06 07 08 09 10 11 12 13 14 15 16 17 18 19 20 21 22 23</Keywords>
        </KeywordLists>
        <Styles>
            <WordsStyle name="DEFAULT" fgColor="000000" bgColor="FFFFFF" fontName="" fontStyle="0" nesting="0" />
            <WordsStyle name="COMMENTS" fgColor="D3D3D3" bgColor="FFFFFF" fontName="" fontStyle="0" nesting="0" />
            <WordsStyle name="LINE COMMENTS" fgColor="3F6564" bgColor="FFFFFF" fontName="" fontStyle="2" nesting="0" />
            <WordsStyle name="NUMBERS" fgColor="E67300" bgColor="FFFFFF" fontName="" fontStyle="1" nesting="0" />
            <WordsStyle name="KEYWORDS1" fgColor="808080" bgColor="FFFFFF" fontName="" fontStyle="2" nesting="0" />
            <WordsStyle name="KEYWORDS2" fgColor="8000FF" bgColor="FFFFFF" fontName="" fontStyle="1" nesting="0" />
            <WordsStyle name="KEYWORDS3" fgColor="DF3748" bgColor="FFFFFF" fontName="" fontStyle="1" nesting="0" />
            <WordsStyle name="KEYWORDS4" fgColor="4FA7FF" bgColor="FFFFFF" fontName="" fontStyle="1" nesting="0" />
            <WordsStyle name="KEYWORDS5" fgColor="ECC4C4" bgColor="FFFFFF" fontName="" fontStyle="0" nesting="0" />
            <WordsStyle name="KEYWORDS6" fgColor="8000FF" bgColor="FFFFFF" fontName="" fontStyle="1" nesting="0" />
            <WordsStyle name="KEYWORDS7" fgColor="FF0080" bgColor="FFFFFF" fontName="" fontStyle="0" nesting="0" />
            <WordsStyle name="KEYWORDS8" fgColor="ECC4C4" bgColor="FFFFFF" fontName="" fontStyle="1" nesting="0" />
            <WordsStyle name="OPERATORS" fgColor="000000" bgColor="FFFFFF" fontName="" fontStyle="0" nesting="0" />
            <WordsStyle name="FOLDER IN CODE1" fgColor="DF3748" bgColor="FFFFFF" fontName="" fontStyle="1" nesting="0" />
            <WordsStyle name="FOLDER IN CODE2" fgColor="000000" bgColor="FFFFFF" fontName="" fontStyle="0" nesting="0" />
            <WordsStyle name="FOLDER IN COMMENT" fgColor="ECC4C4" bgColor="FFFFFF" fontName="" fontStyle="0" nesting="0" />
            <WordsStyle name="DELIMITERS1" fgColor="0DBFFB" bgColor="FFFFFF" fontName="" fontStyle="3" nesting="0" />
            <WordsStyle name="DELIMITERS2" fgColor="0DBFFB" bgColor="FFFFFF" fontName="" fontStyle="3" nesting="0" />
            <WordsStyle name="DELIMITERS3" fgColor="000000" bgColor="FFFFFF" fontName="" fontStyle="0" nesting="0" />
            <WordsStyle name="DELIMITERS4" fgColor="000000" bgColor="FFFFFF" fontName="" fontStyle="0" nesting="0" />
            <WordsStyle name="DELIMITERS5" fgColor="000000" bgColor="FFFFFF" fontName="" fontStyle="0" nesting="0" />
            <WordsStyle name="DELIMITERS6" fgColor="000000" bgColor="FFFFFF" fontName="" fontStyle="0" nesting="0" />
            <WordsStyle name="DELIMITERS7" fgColor="000000" bgColor="FFFFFF" fontName="" fontStyle="0" nesting="0" />
            <WordsStyle name="DELIMITERS8" fgColor="000000" bgColor="FFFFFF" fontName="" fontStyle="0" nesting="0" />
        </Styles>
    </UserLang>
</NotepadPlus>
